{
  "appId": "io.ionic.quickxmarket",
  "appName": "QuickXMarket",
  "bundledWebRuntime": false,
  "npmClient": "npm",
  "webDir": "dist",
  "cordova": {},

  "plugins": {
    "CapacitorHttp": {
      "enabled": true
    },
    "StatusBar": {
      "overlaysWebView": false,
      "style": "DARK",
      "backgroundColor": "#ffffffff"
    },
    "SplashScreen": {
      "launchAutoHide": false,
      "showSpinner": false,
      "androidSplashResourceName": "splash",
      "androidScaleType": "CENTER_CROP",
      "backgroundColor": "#ffffffff"
    }
  }
}
